ssl_checker/__init__.py
ssl_checker/checker.py
ssl_checker/config.py
ssl_checker/database.py
ssl_checker/main.py
ssl_checker/notifier.py
ssl_daily_check-0.1.1.dist-info/LICENSE
ssl_daily_check-0.1.1.dist-info/METADATA
ssl_daily_check-0.1.1.dist-info/WHEEL
ssl_daily_check-0.1.1.dist-info/entry_points.txt
ssl_daily_check-0.1.1.dist-info/RECORD
