Metadata-Version: 2.1
Name: ssl-daily-check
Version: 0.1.1
Summary: Daily SSL certificate monitoring and checking tool
Home-page: https://github.com/rtmax0/ssl-daily-check
License: MIT
Keywords: ssl,certificate,daily,monitoring,security
Author: rtmax0
Author-email: rtmax0@gmail.com
Requires-Python: >=3.8,<4.0
Classifier: Development Status :: 3 - Alpha
Classifier: Intended Audience :: Developers
Classifier: License :: OSI Approved :: MIT License
Classifier: Programming Language :: Python :: 3
Classifier: Programming Language :: Python :: 3.8
Classifier: Programming Language :: Python :: 3.9
Classifier: Programming Language :: Python :: 3.10
Classifier: Programming Language :: Python :: 3.11
Classifier: Programming Language :: Python :: 3.12
Requires-Dist: click (>=8.0.3,<9.0.0)
Requires-Dist: requests (>=2.26.0,<3.0.0)
Project-URL: Repository, https://github.com/rtmax0/ssl-daily-check
